app/__init__.py
app/finrag_server.py
app/models/__init__.py
app/models/dialog.py
app/models/status.py
app/oss/__init__.py
app/oss/download_file.py
FinRAG-0.0.1.dist-info/LICENSE
FinRAG-0.0.1.dist-info/METADATA
FinRAG-0.0.1.dist-info/WHEEL
FinRAG-0.0.1.dist-info/top_level.txt
FinRAG-0.0.1.dist-info/RECORD
